casper_client/__init__.py
casper_client/client.py
casper_client/errors.py
casper_client/grpc/__init__.py
casper_client/grpc/matrix_service_pb2.py
casper_client/grpc/matrix_service_pb2_grpc.py
casper_client/http/__init__.py
casper_client/http/api_client.py
casper_client/models.py
casper_client-0.1.0.dist-info/LICENSE
casper_client-0.1.0.dist-info/METADATA
casper_client-0.1.0.dist-info/WHEEL
casper_client-0.1.0.dist-info/RECORD
