Metadata-Version: 2.1
Name: casper-client
Version: 0.1.0
Summary: Client library for the Casper Vector Database
Home-page: https://github.com/AlexRyzhickov/Casper
License: Apache-2.0
Keywords: vector,search,neural,matching,client
Author: Alexander Ryzhikov
Author-email: makseljoinb@gmail.com
Requires-Python: >=3.10
Classifier: License :: OSI Approved :: Apache Software License
Classifier: Programming Language :: Python :: 3
Classifier: Programming Language :: Python :: 3.10
Classifier: Programming Language :: Python :: 3.11
Classifier: Programming Language :: Python :: 3.12
Classifier: Programming Language :: Python :: 3.13
Requires-Dist: grpcio (>=1.41.0)
Requires-Dist: httpx (>=0.24.0)
Requires-Dist: protobuf (>=3.20.0)
Project-URL: Repository, https://github.com/casper-vdb/python-client
